chatpack/__init__.py
chatpack/_chatpack.cpython-311-x86_64-linux-gnu.so
chatpack/chatpack.pyi
chatpack-0.1.0.dist-info/METADATA
chatpack-0.1.0.dist-info/WHEEL
chatpack-0.1.0.dist-info/licenses/LICENSE
chatpack-0.1.0.dist-info/RECORD
