Metadata-Version: 2.4
Name: chatpack
Version: 0.1.0
Classifier: Development Status :: 4 - Beta
Classifier: Intended Audience :: Developers
Classifier: License :: OSI Approved :: MIT License
Classifier: Programming Language :: Python :: 3
Classifier: Programming Language :: Python :: 3.8
Classifier: Programming Language :: Python :: 3.9
Classifier: Programming Language :: Python :: 3.10
Classifier: Programming Language :: Python :: 3.11
Classifier: Programming Language :: Python :: 3.12
Classifier: Programming Language :: Rust
Classifier: Topic :: Software Development :: Libraries :: Python Modules
Classifier: Topic :: Text Processing
License-File: LICENSE
Summary: High-performance Python bindings for chatpack - parse chat exports from Telegram, WhatsApp, Instagram, and Discord
Keywords: chat,parser,telegram,whatsapp,instagram,discord,nlp,llm
License: MIT
Requires-Python: >=3.8
Project-URL: Documentation, https://docs.rs/chatpack
Project-URL: Homepage, https://github.com/berektassuly/chatpack
Project-URL: Repository, https://github.com/berektassuly/chatpack-py
